hello.py
adsk_amptest-0.0.1.dist-info/METADATA
adsk_amptest-0.0.1.dist-info/WHEEL
adsk_amptest-0.0.1.dist-info/top_level.txt
adsk_amptest-0.0.1.dist-info/RECORD
